pysftp_extension/__init__.py
pysftp_extension/exceptions.py
pysftp_extension/helpers.py
pysftp_extension-0.2.13.dist-info/LICENSE.txt
pysftp_extension-0.2.13.dist-info/METADATA
pysftp_extension-0.2.13.dist-info/WHEEL
pysftp_extension-0.2.13.dist-info/top_level.txt
pysftp_extension-0.2.13.dist-info/RECORD
