Metadata-Version: 2.1
Name: pysftp-extension
Version: 0.2.13
Summary: A friendly face on SFTP
Home-page: https://github.com/achillis2/pysftp_extension
Author: Ding Li
Author-email: dingli@gmail.com
License: BSD
Download-URL: https://pypi.python.org/pypi/pysftp_extension
Keywords: sftp ssh ftp internet
Platform: any
Classifier: Development Status :: 4 - Beta
Classifier: License :: OSI Approved :: BSD License
Classifier: Programming Language :: Python
Classifier: Programming Language :: Python :: 2
Classifier: Programming Language :: Python :: 2.7
Classifier: Programming Language :: Python :: 3
Classifier: Programming Language :: Python :: 3.3
Classifier: Programming Language :: Python :: 3.4
Classifier: Programming Language :: Python :: 3.5
Classifier: Programming Language :: Python :: Implementation :: CPython
License-File: LICENSE.txt
Requires-Dist: paramiko (==2.9.2)
